entropy_cli/__init__.py
entropy_cli/build.py
entropy_cli/build_project.py
entropy_cli/local_test.py
entropy_cli/login.py
entropy_cli/main.py
entropy_cli/sample_files.py
entropy_cli/utils.py
entropy_cli-0.1.1.dist-info/entry_points.txt
entropy_cli-0.1.1.dist-info/WHEEL
entropy_cli-0.1.1.dist-info/METADATA
entropy_cli-0.1.1.dist-info/RECORD
