Metadata-Version: 2.1
Name: entropy-cli
Version: 0.1.1
Summary: the command line tool for seamless code projects
Author: perseus.yang
Author-email: ry82@cornell.edu
Requires-Python: >=3.7,<4.0
Classifier: Programming Language :: Python :: 3
Classifier: Programming Language :: Python :: 3.10
Classifier: Programming Language :: Python :: 3.7
Classifier: Programming Language :: Python :: 3.8
Classifier: Programming Language :: Python :: 3.9
Requires-Dist: awscli (>=1.22.23,<2.0.0)
Requires-Dist: boto3 (>=1.20.23,<2.0.0)
Requires-Dist: requests (>=2.26.0,<3.0.0)
